cosmotile/__init__.py
cosmotile/__main__.py
cosmotile/py.typed
cosmotile-0.1.1.dist-info/entry_points.txt
cosmotile-0.1.1.dist-info/LICENSE
cosmotile-0.1.1.dist-info/WHEEL
cosmotile-0.1.1.dist-info/METADATA
cosmotile-0.1.1.dist-info/RECORD
