Metadata-Version: 2.1
Name: cosmotile
Version: 0.1.1
Summary: Cosmotile
Home-page: https://github.com/steven-murray/cosmotile
License: MIT
Author: Steven Murray
Author-email: steven.g.murray@asu.edu
Requires-Python: >=3.8,<4.0
Classifier: Development Status :: 2 - Pre-Alpha
Classifier: License :: OSI Approved :: MIT License
Classifier: Programming Language :: Python :: 3
Classifier: Programming Language :: Python :: 3.8
Classifier: Programming Language :: Python :: 3.9
Classifier: Programming Language :: Python :: 3.10
Classifier: Programming Language :: Python :: 3.11
Requires-Dist: astropy (>=5.1.1,<6.0.0)
Requires-Dist: astropy-healpix (>=0.7,<0.8)
Requires-Dist: click (>=8.0.1)
Requires-Dist: numpy (>=1.23.4,<2.0.0)
Requires-Dist: scipy (>=1.9.3,<2.0.0)
Project-URL: Changelog, https://github.com/steven-murray/cosmotile/releases
Project-URL: Documentation, https://cosmotile.readthedocs.io
Project-URL: Repository, https://github.com/steven-murray/cosmotile
